karuha/__init__.py
karuha/__main__.py
karuha/bot.py
karuha/config.py
karuha/exception.py
karuha/logger.py
karuha/plugin_server.py
karuha/py.typed
karuha/runner.py
karuha/session.py
karuha/store.py
karuha/version.py
karuha/command/__init__.py
karuha/command/collection.py
karuha/command/command.py
karuha/command/decoractor.py
karuha/command/parser.py
karuha/command/rule.py
karuha/command/session.py
karuha/data/__init__.py
karuha/data/cache.py
karuha/data/data.py
karuha/data/meta.py
karuha/data/model.py
karuha/data/sub.py
karuha/data/topic.py
karuha/data/types.py
karuha/data/user.py
karuha/event/__init__.py
karuha/event/base.py
karuha/event/bot.py
karuha/event/command.py
karuha/event/message.py
karuha/event/plugin.py
karuha/event/sys.py
karuha/service/__init__.py
karuha/service/base.py
karuha/service/bot.py
karuha/service/info.py
karuha/service/topic.py
karuha/service/user.py
karuha/text/__init__.py
karuha/text/convert.py
karuha/text/drafty.py
karuha/text/message.py
karuha/text/textchain.py
karuha/utils/__init__.py
karuha/utils/argparse.py
karuha/utils/context.py
karuha/utils/decode.py
karuha/utils/dispatcher.py
karuha/utils/event_catcher.py
karuha/utils/gathering.py
karuha/utils/invoker.py
karuha/utils/locks.py
karuha/utils/proxy_propery.py
KaruhaBot-0.2.4.dist-info/LICENSE
KaruhaBot-0.2.4.dist-info/METADATA
KaruhaBot-0.2.4.dist-info/WHEEL
KaruhaBot-0.2.4.dist-info/top_level.txt
KaruhaBot-0.2.4.dist-info/RECORD
