Metadata-Version: 2.1
Name: KaruhaBot
Version: 0.2.4
Summary: A simple Tinode chatbot framework.
Home-page: https://github.com/Visecy/Karuha
Author: Visecy
Author-email: Visecy <Visecy@visecy.org>
Maintainer: Ovizro
Maintainer-email: Ovizro <Ovizro@visecy.org>
License: Apache 2.0
Project-URL: repository, https://github.com/Visecy/Karuha
Classifier: Development Status :: 5 - Production/Stable
Classifier: License :: OSI Approved :: Apache Software License
Classifier: Programming Language :: Python :: 3
Classifier: Programming Language :: Python :: 3 :: Only
Classifier: Programming Language :: Python :: 3.8
Classifier: Programming Language :: Python :: 3.9
Classifier: Programming Language :: Python :: 3.10
Classifier: Programming Language :: Python :: 3.11
Classifier: Programming Language :: Python :: 3.12
Classifier: Topic :: Software Development :: Libraries :: Python Modules
Classifier: Topic :: Communications :: Chat
Requires-Python: >=3.8
License-File: LICENSE
Requires-Dist: typing-extensions>=4.9
Requires-Dist: grpcio>=1.40.0
Requires-Dist: tinode-grpc>=0.20.0b3
Requires-Dist: pydantic>=2.9
Requires-Dist: aiohttp>=3.7
Requires-Dist: aiofiles>=23.1
Requires-Dist: puremagic>=1.20
Provides-Extra: all
Requires-Dist: KaruhaBot[attachment]; extra == "all"
Requires-Dist: KaruhaBot[data]; extra == "all"
Provides-Extra: attachment
Requires-Dist: KaruhaBot[image]; extra == "attachment"
Requires-Dist: KaruhaBot[audio]; extra == "attachment"
Provides-Extra: audio
Requires-Dist: soundfile>=0.12; extra == "audio"
Requires-Dist: numpy>=1.21; extra == "audio"
Provides-Extra: data
Requires-Dist: greenback; extra == "data"
Provides-Extra: dev
Requires-Dist: KaruhaBot[all]; extra == "dev"
Requires-Dist: KaruhaBot[lint]; extra == "dev"
Requires-Dist: pytest; extra == "dev"
Requires-Dist: pytest-asyncio; extra == "dev"
Requires-Dist: coverage; extra == "dev"
Provides-Extra: image
Requires-Dist: pillow>=10.0; extra == "image"
Provides-Extra: lint
Requires-Dist: flake8>=6.1; extra == "lint"
